PyautoPDF/PdfAutomationModule.py
PyautoPDF/__init__.py
PyautoPDF-0.1.5.dist-info/LICENSE
PyautoPDF-0.1.5.dist-info/METADATA
PyautoPDF-0.1.5.dist-info/WHEEL
PyautoPDF-0.1.5.dist-info/top_level.txt
PyautoPDF-0.1.5.dist-info/RECORD
