Metadata-Version: 2.1
Name: PyautoPDF
Version: 0.1.5
Summary: Business Report Automation
Author: Shailesh Suthar
Author-email: shaileshsuthar676@gmail.com
License: MIT
Keywords: python,PDF,PDF automation,documentation,report automation,report
Classifier: Development Status :: 1 - Planning
Classifier: Intended Audience :: Developers
Classifier: Operating System :: MacOS :: MacOS X
Classifier: Operating System :: Microsoft :: Windows
Classifier: License :: OSI Approved :: MIT License
Classifier: Programming Language :: Python
Classifier: Programming Language :: Python :: 3.6
Classifier: Programming Language :: Python :: 3.7
Classifier: Programming Language :: Python :: 3.8
Classifier: Programming Language :: Python :: 3.9
License-File: LICENSE
Requires-Dist: openpyxl
Requires-Dist: pywin32
